mocktopus/__init__.py
mocktopus/cli.py
mocktopus/core.py
mocktopus/cost_tracker.py
mocktopus/llm_openai.py
mocktopus/pytest_plugin.py
mocktopus/recorder.py
mocktopus/server.py
mocktopus-0.2.0.dist-info/METADATA
mocktopus-0.2.0.dist-info/WHEEL
mocktopus-0.2.0.dist-info/entry_points.txt
mocktopus-0.2.0.dist-info/licenses/LICENSE
mocktopus-0.2.0.dist-info/RECORD
