Metadata-Version: 2.4
Name: mocktopus
Version: 0.2.0
Summary: 🐙 Multi-armed mocks for LLM apps - Drop-in replacement for OpenAI/Anthropic APIs for deterministic testing
Project-URL: Homepage, https://github.com/evalops/mocktopus
Author: Jonathan Haas
License: MIT
License-File: LICENSE
Requires-Python: >=3.9
Requires-Dist: aiohttp>=3.8.0
Requires-Dist: click>=8.1
Requires-Dist: pyyaml>=6.0
Requires-Dist: typing-extensions>=4.9
Provides-Extra: dev
Requires-Dist: mypy>=1.0; extra == 'dev'
Requires-Dist: pytest-asyncio>=0.21; extra == 'dev'
Requires-Dist: pytest>=7.0; extra == 'dev'
Requires-Dist: types-pyyaml; extra == 'dev'
Provides-Extra: test
Requires-Dist: pytest-asyncio>=0.21; extra == 'test'
Requires-Dist: pytest>=7.0; extra == 'test'
